a_pandas_ex_dillpickle/README.MD
a_pandas_ex_dillpickle/__init__.py
a_pandas_ex_dillpickle/requirements.txt
a_pandas_ex_dillpickle/thirdparty.json
a_pandas_ex_dillpickle-0.10.dist-info/LICENSE.rst
a_pandas_ex_dillpickle-0.10.dist-info/METADATA
a_pandas_ex_dillpickle-0.10.dist-info/WHEEL
a_pandas_ex_dillpickle-0.10.dist-info/top_level.txt
a_pandas_ex_dillpickle-0.10.dist-info/RECORD
