Metadata-Version: 2.1
Name: a-pandas-ex-dillpickle
Version: 0.10
Summary: Pickle pandas DataFrames without AttributeError: Can't pickle local object ... 
Home-page: https://github.com/hansalemaos/a_pandas_ex_dillpickle
Author: Johannes Fischer
Author-email: <aulasparticularesdealemaosp@gmail.com>
License: MIT
Keywords: pandas,pickle,dill
Classifier: Development Status :: 4 - Beta
Classifier: Programming Language :: Python :: 3 :: Only
Classifier: Programming Language :: Python :: 3.9
Classifier: Topic :: Scientific/Engineering :: Visualization
Classifier: Topic :: Software Development :: Libraries :: Python Modules
Classifier: Topic :: Text Editors :: Text Processing
Classifier: Topic :: Text Processing :: General
Classifier: Topic :: Text Processing :: Indexing
Classifier: Topic :: Text Processing :: Filters
Classifier: Topic :: Utilities
License-File: LICENSE.rst
Requires-Dist: dill
Requires-Dist: pandas
Requires-Dist: touchtouch
